deskorganizer/__init__
deskorganizer/organizefiles.py
deskorganizer-0.0.2.dist-info/METADATA
deskorganizer-0.0.2.dist-info/WHEEL
deskorganizer-0.0.2.dist-info/licenses/LICENSE
deskorganizer-0.0.2.dist-info/RECORD
