Metadata-Version: 2.4
Name: deskorganizer
Version: 0.0.2
Summary: desktop file organizer
Project-URL: Homepage, https://github.com/kylejacobCS/DeskOrganizer
Project-URL: Issues, https://github.com/kylejacobCS/DeskOrganizer/issues
Author-email: kappa <kappann01@gmail.com>
License-File: LICENSE
Classifier: License :: OSI Approved :: GNU General Public License v3 (GPLv3)
Classifier: Operating System :: OS Independent
Classifier: Programming Language :: Python :: 3
Requires-Python: >=3.0
Requires-Dist: pandas
